[
  {
    "si_do_code": 11,
    "si_do": "서울특별시"
  },
  {
    "si_do_code": 26,
    "si_do": "부산광역시"
  },
  {
    "si_do_code": 27,
    "si_do": "대구광역시"
  },
  {
    "si_do_code": 28,
    "si_do": "인천광역시"
  },
  {
    "si_do_code": 29,
    "si_do": "광주광역시"
  },
  {
    "si_do_code": 30,
    "si_do": "대전광역시"
  },
  {
    "si_do_code": 31,
    "si_do": "울산광역시"
  },
  {
    "si_do_code": 36,
    "si_do": "세종특별자치시"
  },
  {
    "si_do_code": 41,
    "si_do": "경기도"
  },
  {
    "si_do_code": 42,
    "si_do": "강원도"
  },
  {
    "si_do_code": 43,
    "si_do": "충청북도"
  },
  {
    "si_do_code": 44,
    "si_do": "충청남도"
  },
  {
    "si_do_code": 45,
    "si_do": "전라북도"
  },
  {
    "si_do_code": 46,
    "si_do": "전라남도"
  },
  {
    "si_do_code": 47,
    "si_do": "경상북도"
  },
  {
    "si_do_code": 48,
    "si_do": "경상남도"
  },
  {
    "si_do_code": 50,
    "si_do": "제주특별자치도"
  }
]